parametric_si/__init__.py
parametric_si/ci.py
parametric_si/cv.py
parametric_si/lars.py
parametric_si/lars_si.py
parametric_si/lasso.py
parametric_si/lasso_si.py
parametric_si/p_value.py
parametric_si/probability.py
parametric_si/quadratic.py
parametric_si/sfs.py
parametric_si/sfs_si.py
parametric_si/si.py
parametric_si/si_cv.py
parametric_si-1.0.4.dist-info/LICENSE
parametric_si-1.0.4.dist-info/METADATA
parametric_si-1.0.4.dist-info/WHEEL
parametric_si-1.0.4.dist-info/top_level.txt
parametric_si-1.0.4.dist-info/RECORD
