Metadata-Version: 2.1
Name: parametric-si
Version: 1.0.4
Summary: tools for parametric selective inference
Home-page: https://github.com/takeuchi-lab/parametric-si
Author: Takeuchi Lab
Author-email: miwa.daiki.mllab.nit@gmail.com
License: MIT License
Platform: UNKNOWN
License-File: LICENSE
Requires-Dist: numpy
Requires-Dist: scipy
Requires-Dist: portion
Requires-Dist: sklearn
